README.md
README.txt
setup.py
cs/__init__.py
cs.portlet.icalendar.egg-info/PKG-INFO
cs.portlet.icalendar.egg-info/SOURCES.txt
cs.portlet.icalendar.egg-info/dependency_links.txt
cs.portlet.icalendar.egg-info/entry_points.txt
cs.portlet.icalendar.egg-info/namespace_packages.txt
cs.portlet.icalendar.egg-info/not-zip-safe
cs.portlet.icalendar.egg-info/requires.txt
cs.portlet.icalendar.egg-info/top_level.txt
cs/portlet/__init__.py
cs/portlet/icalendar/__init__.py
cs/portlet/icalendar/calendarportlet.pt
cs/portlet/icalendar/calendarportlet.py
cs/portlet/icalendar/configure.zcml
cs/portlet/icalendar/rebuild_i18n.sh
cs/portlet/icalendar/tests.py
cs/portlet/icalendar/locales/cs.portlet.icalendar-manual.pot
cs/portlet/icalendar/locales/cs.portlet.icalendar.pot
cs/portlet/icalendar/locales/es/LC_MESSAGES/cs.portlet.icalendar.po
cs/portlet/icalendar/locales/eu/LC_MESSAGES/cs.portlet.icalendar.po
cs/portlet/icalendar/profiles/default/metadata.xml
cs/portlet/icalendar/profiles/default/portlets.xml
docs/HISTORY.txt
docs/INSTALL.txt
docs/LICENSE.GPL
docs/LICENSE.txt