Metadata-Version: 1.1
Name: cs.portlet.icalendar
Version: 1.0
Summary: A portlet to show a icalendar file events in a portlet
Home-page: http://github.com/codesyntax/cs.portlet.icalendar/
Author: Mikel Larreategi
Author-email: mlarreategi@codesyntax.com
License: GPL
Keywords: plone portlet icalendar
Platform: UNKNOWN
Classifier: Framework :: Plone
Classifier: Programming Language :: Python
